LICENSE
NOTICE.txt
README.md
setup.py
pyctory/__init__.py
pyctory/factory.py
pyctory.egg-info/PKG-INFO
pyctory.egg-info/SOURCES.txt
pyctory.egg-info/dependency_links.txt
pyctory.egg-info/requires.txt
pyctory.egg-info/top_level.txt
pyctory/classes/__init__.py
pyctory/classes/base.py
pyctory/classes/buffer.py
pyctory/classes/connects.py
pyctory/classes/item.py
pyctory/classes/iteminfo.py
pyctory/classes/processor.py
pyctory/classes/scene.py
pyctory/classes/sink.py
pyctory/classes/source.py
pyctory/config/__init__.py
pyctory/config/config.py
pyctory/context/__init__.py
pyctory/context/context.py
pyctory/utils/__init__.py
pyctory/utils/data.py
pyctory/utils/render.py
pyctory/utils/rules.py
pyctory/utils/watcher.py
pyctory/utils/watcher_utils.py