Metadata-Version: 2.1
Name: pyctory
Version: 0.0.1
Summary: factory pipeline scheduling simulator with python
Home-page: https://github.com/PiperLiu/pyctory
Author: Piper Liu
Author-email: piperliu@qq.com
Classifier: Programming Language :: Python :: 3.6
Classifier: Programming Language :: Python :: 3.7
Classifier: Programming Language :: Python :: 3.8
Classifier: Programming Language :: Python :: 3.9
Classifier: Programming Language :: Python :: 3.10
Classifier: Operating System :: OS Independent
Requires-Python: >=3.6
License-File: LICENSE
License-File: NOTICE.txt
